kantan_agents_tools/__init__.py
kantan_agents_tools/browser.py
kantan_agents_tools/context.py
kantan_agents_tools/errors.py
kantan_agents_tools/exec.py
kantan_agents_tools/fs.py
kantan_agents_tools/policy.py
kantan_agents_tools/provider.py
kantan_agents_tools/toolset.py
kantan_agents_tools/trace.py
kantan_agents_tools/utils.py
kantan_agents_tools/web.py
kantan_agents_tools-0.1.1.dist-info/licenses/LICENSE
kantan_agents_tools-0.1.1.dist-info/METADATA
kantan_agents_tools-0.1.1.dist-info/WHEEL
kantan_agents_tools-0.1.1.dist-info/entry_points.txt
kantan_agents_tools-0.1.1.dist-info/top_level.txt
kantan_agents_tools-0.1.1.dist-info/RECORD
