Metadata-Version: 2.4
Name: kantan-agents-tools
Version: 0.1.1
Summary: Basic tools of kantan-agents
Requires-Python: >=3.10
License-File: LICENSE
Requires-Dist: kantan-agents>=0.1.3
Requires-Dist: beautifulsoup4>=4.12.3
Requires-Dist: duckduckgo-search>=6.3.0
Requires-Dist: pathspec>=0.12.1
Requires-Dist: playwright>=1.45.0
Requires-Dist: tavily-python>=0.5.0
Requires-Dist: unidiff>=0.7.5
Dynamic: license-file
